[{"spanishExample":"No he usado el nuevo puente en el parque.","englishTranslation":"I haven’t used the new bridge in the park.","spanglish":"esp","vocabIncluded":["\"el\": \"the\" for masculine nouns","\"en\": \"in\"","\"no\": \"not\", or \"n't\" in \"didn't\", \"wouldn't\", etc.","he: \"have\", \"I have\" before a participle (Haber, present, 1st person)","nuevo: \"new\" (adjective typically used with Ser)","parque: park (masc. noun)","puente: bridge (masc. noun)","usado: used (Usar participle)"],"vocabComplete":true,"spanishAudioLa":"https://dbexamples.s3.us-east-2.amazonaws.com/dbexamples/ex15922la.mp3","englishAudio":"https://dbexamples.s3.us-east-2.amazonaws.com/dbexamples/ex15922en.mp3","recordId":15922,"dateCreated":"2024-01-30T19:52:36Z","dateModified":"2024-11-14T22:00:11Z","errorCoachReport":false},{"spanishExample":"Nunca ganamos, es imposible.","englishTranslation":"We never win, it’s impossible.","spanglish":"esp","vocabIncluded":["es: \"is\", \"he/she/it is\" (Ser, present, 3rd person)","ganamos: win/earn, we win/earn (Ganar, present, 1st person plural)","imposible: impossible (adjective)","nunca: \"never\" (adverb)"],"vocabComplete":true,"spanishAudioLa":"https://dbexamples.s3.us-east-2.amazonaws.com/dbexamples/ex15923la.mp3","englishAudio":"https://dbexamples.s3.us-east-2.amazonaws.com/dbexamples/ex15923en.mp3","recordId":15923,"dateCreated":"2024-01-30T19:52:36Z","dateModified":"2024-11-14T22:00:11Z","errorCoachReport":false},{"spanishExample":"Puedes usarlo en la plaza, pero no en ningún otro sitio.","englishTranslation":"You can use it at the square, but not at any other site.","spanglish":"esp","vocabIncluded":["\"en\": \"at\" indicating location","\"la\": \"the\" for feminine nouns","\"no\": \"not\", or \"n't\" in \"didn't\", \"wouldn't\", etc.","\"pero\": \"but\"","ninguno/ningún/ninguna: \"none\", \"no\" (adjective)","otro/otra: \"other\", \"another\" (adjective)","plaza: plaza/square (fem. noun)","puedes: \"can\", \"you can\" (Poder, present, 2nd person)","sitio: site (masc. noun)","usarlo: to use (Usar infinitive) + him/it (masc)"],"vocabComplete":true,"spanishAudioLa":"","englishAudio":"","recordId":15924,"dateCreated":"2024-01-30T19:52:36Z","dateModified":"2024-05-02T16:42:20Z","errorCoachReport":false},{"spanishExample":"Quiero que pague el café, porque yo siempre pago.","englishTranslation":"I want him to pay for the coffee, because I always pay.","spanglish":"esp","vocabIncluded":["\"el\": \"the\" for masculine nouns","\"que\", meaning \"that\" as a conjunction (even in cases where \"that\" disappears in English)","café: coffee (masc. noun)","pago: pay, I pay (Pagar, present, 1st person)","pague: pay, he/she/it pay (Pagar, subjunctive, 3rd person)","porque: \"because\" (conjunction)","quiero: \"want\", \"I want\" (Querer, present, 1st person)","siempre: \"always\" (adverb)","yo: \"I\", subject pronoun"],"vocabComplete":true,"spanishAudioLa":"https://dbexamples.s3.us-east-2.amazonaws.com/dbexamples/ex15925la.mp3","englishAudio":"https://dbexamples.s3.us-east-2.amazonaws.com/dbexamples/ex15925en.mp3","recordId":15925,"dateCreated":"2024-01-30T19:52:36Z","dateModified":"2024-11-14T22:00:11Z","errorCoachReport":false},{"spanishExample":"No creo que funcione, pero igual díselo.","englishTranslation":"I don’t think it will work, but still tell it to him.","spanglish":"esp","vocabIncluded":["\"no\": \"not\", or \"n't\" in \"didn't\", \"wouldn't\", etc.","\"pero\": \"but\"","\"que\", meaning \"that\" as a conjunction (even in cases where \"that\" disappears in English)","creo: believe, I believe (Creer, present, 1st person)","díselo: tell it to him/her (Decir, imperative contraction) NEEDS WORK","funcione: function/work, he/she/it function/work (Funcionar, subjunctive, 3rd person)","igual: in the same way / equally (adverb)"],"vocabComplete":true,"spanishAudioLa":"https://dbexamples.s3.us-east-2.amazonaws.com/dbexamples/ex15926la.mp3","englishAudio":"https://dbexamples.s3.us-east-2.amazonaws.com/dbexamples/ex15926en.mp3","recordId":15926,"dateCreated":"2024-01-30T19:52:36Z","dateModified":"2024-11-14T22:00:11Z","errorCoachReport":false},{"spanishExample":"No gano mucho dinero porque no me pagan mucho.","englishTranslation":"I don’t earn much money because they don’t pay me much.","spanglish":"esp","vocabIncluded":["\"no\": \"not\", or \"n't\" in \"didn't\", \"wouldn't\", etc.","dinero: money (masc. noun)","gano: win/earn, I win/earn (Ganar, present, 1st person)","me: \"me\" as an indirect object (\"to me\", \"for me\")","mucho: \"a lot\", \"much\" (adjective)","mucho: \"much\", \"a lot\" (adverb)","pagan: pay, they pay (Pagar, present, 3rd person plural)","porque: \"because\" (conjunction)"],"vocabComplete":true,"spanishAudioLa":"https://dbexamples.s3.us-east-2.amazonaws.com/dbexamples/ex15927la.mp3","englishAudio":"https://dbexamples.s3.us-east-2.amazonaws.com/dbexamples/ex15927en.mp3","recordId":15927,"dateCreated":"2024-01-30T19:52:36Z","dateModified":"2024-11-14T22:00:11Z","errorCoachReport":false},{"spanishExample":"¿Ganaste dinero? ¡Dáselo!","englishTranslation":"Did you win money? Give it to him!","spanglish":"esp","vocabIncluded":["dinero: money (masc. noun)","dáselo: give it to him/her (Dar, imperative contraction)","ganaste: won/earned, you won/earned (Ganar, preterite, 2nd person)"],"vocabComplete":true,"spanishAudioLa":"","englishAudio":"","recordId":15928,"dateCreated":"2024-01-30T19:52:36Z","dateModified":"2024-05-02T16:43:14Z","errorCoachReport":false},{"spanishExample":"¡Pague en la entrada!","englishTranslation":"(Formal) Pay at the entrance!","spanglish":"esp","vocabIncluded":["\"en\": \"at\" indicating location","\"la\": \"the\" for feminine nouns","entrada: entrance (fem. noun)","pague: pay (Pagar formal imperative)"],"vocabComplete":true,"spanishAudioLa":"","englishAudio":"","recordId":15929,"dateCreated":"2024-01-30T19:52:36Z","dateModified":"2024-05-02T14:53:38Z","errorCoachReport":false},{"spanishExample":"No la he conseguido, ¡dámela!","englishTranslation":"I haven’t gotten it(f), give it to me!","spanglish":"esp","vocabIncluded":["\"la\": \"her\" or \"it\" as a direct object","\"no\": \"not\", or \"n't\" in \"didn't\", \"wouldn't\", etc.","conseguido: acquired/gotten (Conseguir participle)","dámela: give it/her to me (Dar, imperative contraction)","he: \"have\", \"I have\" before a participle (Haber, present, 1st person)"],"vocabComplete":true,"spanishAudioLa":"https://dbexamples.s3.us-east-2.amazonaws.com/dbexamples/ex15930la.mp3","englishAudio":"https://dbexamples.s3.us-east-2.amazonaws.com/dbexamples/ex15930en.mp3","recordId":15930,"dateCreated":"2024-01-30T19:52:36Z","dateModified":"2024-11-14T22:00:11Z","errorCoachReport":false},{"spanishExample":"Si sigues la acera, llegarás a la dirección correcta.","englishTranslation":"If you follow the sidewalk, you’ll get to the right address.","spanglish":"esp","vocabIncluded":["\"a\": \"to\", indicating direction/movement","\"la\": \"the\" for feminine nouns","\"si\": \"if\" or \"whether\"","acera: sidewalk (fem. noun)","correcto: correct/ right (adjective)","dirección: direction/address (fem. noun)","sigues: continue/follow, you continue/follow (Seguir, present, 2nd person)"],"vocabComplete":false,"spanishAudioLa":"","englishAudio":"","recordId":15931,"dateCreated":"2024-01-30T19:52:36Z","dateModified":"2024-03-14T23:16:33Z","errorCoachReport":true},{"spanishExample":"Siempre lo consigo, pero nunca lo usamos.","englishTranslation":"I always get it, but we never use it.","spanglish":"esp","vocabIncluded":["\"lo\": \"him\" or \"it\" as a direct object","\"pero\": \"but\"","consigo: acquire/get, I acquire/get (Conseguir, present, 1st person)","nunca: \"never\" (adverb)","siempre: \"always\" (adverb)","usamos: use, we use (Usar, present, 1st person plural)"],"vocabComplete":true,"spanishAudioLa":"https://dbexamples.s3.us-east-2.amazonaws.com/dbexamples/ex15932la.mp3","englishAudio":"https://dbexamples.s3.us-east-2.amazonaws.com/dbexamples/ex15932en.mp3","recordId":15932,"dateCreated":"2024-01-30T19:52:36Z","dateModified":"2024-11-14T22:00:11Z","errorCoachReport":false},{"spanishExample":"Quiero que él gane porque es excelente.","englishTranslation":"I want him to win because he is excellent.","spanglish":"esp","vocabIncluded":["\"que\", meaning \"that\" as a conjunction (even in cases where \"that\" disappears in English)","es: \"is\", \"he/she/it is\" (Ser, present, 3rd person)","excelente: excellent (adjective)","gane: win/earn, he/she/it win/earn (Ganar, subjunctive, 3rd person)","porque: \"because\" (conjunction)","quiero: \"want\", \"I want\" (Querer, present, 1st person)","él: \"he\", subject pronoun"],"vocabComplete":true,"spanishAudioLa":"https://dbexamples.s3.us-east-2.amazonaws.com/dbexamples/ex15933la.mp3","englishAudio":"https://dbexamples.s3.us-east-2.amazonaws.com/dbexamples/ex15933en.mp3","recordId":15933,"dateCreated":"2024-01-30T19:52:36Z","dateModified":"2024-11-14T22:00:11Z","errorCoachReport":false},{"spanishExample":"Si usas eso en la carretera, será raro, así que dámelo.","englishTranslation":"If you use that on the road, it will be weird, so give it to me.","spanglish":"esp","vocabIncluded":["\"en\": \"on\"","\"eso\": \"that\", neuter (without a gendered noun)","\"la\": \"the\" for feminine nouns","\"si\": \"if\" or \"whether\"","así que: \"so\", \"so that\", \"such that\" (idiom)","carretera: road (fem. noun)","dámelo: give it/him to me (Dar, imperative contraction)","raro: rare/weird (adjective)","será: \"will be\", \"he/she/it will be\" (Ser, future, 3rd person)","usas: use, you use (Usar, present, 2nd person)"],"vocabComplete":true,"spanishAudioLa":"","englishAudio":"","recordId":15934,"dateCreated":"2024-01-30T19:52:36Z","dateModified":"2024-05-02T16:28:03Z","errorCoachReport":false},{"spanishExample":"Tú nunca ganas y ella siempre consigue lo que quiere.","englishTranslation":"You never win and she always gets what she wants.","spanglish":"esp","vocabIncluded":["\"lo que\": \"what\" as a connector between phrases","\"y\": \"and\" between clauses","consigue: acquires/gets, he/she/it acquires/gets (Conseguir, present, 3rd person)","ella: \"she\", subject pronoun","ganas: win/earn, you win/earn (Ganar, present, 2nd person)","nunca: \"never\" (adverb)","quiere: \"wants\", \"he/she/it wants\" (Querer, present, 3rd person)","siempre: \"always\" (adverb)","tú: \"you\", subject pronoun"],"vocabComplete":true,"spanishAudioLa":"https://dbexamples.s3.us-east-2.amazonaws.com/dbexamples/ex15935la.mp3","englishAudio":"https://dbexamples.s3.us-east-2.amazonaws.com/dbexamples/ex15935en.mp3","recordId":15935,"dateCreated":"2024-01-30T19:52:36Z","dateModified":"2024-11-14T22:00:11Z","errorCoachReport":false},{"spanishExample":"Siempre usa el puente para llegar al otro estado.","englishTranslation":"She always uses the bridge to get to the other state.","spanglish":"esp","vocabIncluded":["\"el\": \"the\" for masculine nouns","al: \"to the\" before a masculine noun","estado: state (place) (masc. noun)","llegar: to arrive (Llegar infinitive)","otro/otra: \"other\", \"another\" (adjective)","para: \"in order\", \"in order to\" before an infinitive","puente: bridge (masc. noun)","siempre: \"always\" (adverb)","usa: uses, he/she/it uses (Usar, present, 3rd person)"],"vocabComplete":true,"spanishAudioLa":"https://dbexamples.s3.us-east-2.amazonaws.com/dbexamples/ex15936la.mp3","englishAudio":"https://dbexamples.s3.us-east-2.amazonaws.com/dbexamples/ex15936en.mp3","recordId":15936,"dateCreated":"2024-01-30T19:52:36Z","dateModified":"2024-11-14T22:00:11Z","errorCoachReport":false},{"spanishExample":"No puede conseguir nada en esa zona de la ciudad.","englishTranslation":"He can’t get anything in that area of the city.","spanglish":"esp","vocabIncluded":["\"de\": \"of\" as in \"type of\"","\"en\": \"in\"","\"la\": \"the\" for feminine nouns","\"no\": \"not\", or \"n't\" in \"didn't\", \"wouldn't\", etc.","ciudad: city (fem. noun)","conseguir: to acquire/to get(Conseguir infinitive)","esa: \"that...\" before a feminine noun","nada: \"nothing\" (pronoun)","puede: \"can\", \"he/she/it can\" (Poder, present, 3rd person)","zona: zone/area (fem. noun)"],"vocabComplete":true,"spanishAudioLa":"https://dbexamples.s3.us-east-2.amazonaws.com/dbexamples/ex15937la.mp3","englishAudio":"https://dbexamples.s3.us-east-2.amazonaws.com/dbexamples/ex15937en.mp3","recordId":15937,"dateCreated":"2024-01-30T19:52:36Z","dateModified":"2024-11-14T22:00:11Z","errorCoachReport":false},{"spanishExample":"¡Consiga una nueva zona para nuestro juego!","englishTranslation":"(Formal) Get a new area for our game!","spanglish":"esp","vocabIncluded":["\"nuestro\": \"our\" or \"ours\"","\"para\": \"for\", as in \"intended for\"","\"una\": \"a\" or \"an\" with feminine nouns","consiga: acquire (Conseguir, formal imperative)","juego: game (masc. noun)","nuevo: \"new\" (adjective typically used with Ser)","zona: zone/area (fem. noun)"],"vocabComplete":true,"spanishAudioLa":"https://dbexamples.s3.us-east-2.amazonaws.com/dbexamples/ex15938la.mp3","englishAudio":"https://dbexamples.s3.us-east-2.amazonaws.com/dbexamples/ex15938en.mp3","recordId":15938,"dateCreated":"2024-01-30T19:52:36Z","dateModified":"2024-11-14T22:00:11Z","errorCoachReport":false},{"spanishExample":"No ganó y tienes que decírselo.","englishTranslation":"He didn’t win and you have to tell it to him.","spanglish":"esp","vocabIncluded":["\"no\": \"not\", or \"n't\" in \"didn't\", \"wouldn't\", etc.","\"y\": \"and\" between clauses","decírselo: to tell it to him/her/them (Decir infinitive+contraction)","ganó: won/earned, he/she/it won/earned (Ganar, preterite, 3rd person)","tienes: \"have\", \"you have\" (Tener, present, 2nd person)","using Tener with \"que\" to indicate obligation"],"vocabComplete":true,"spanishAudioLa":"https://dbexamples.s3.us-east-2.amazonaws.com/dbexamples/ex15939la.mp3","englishAudio":"https://dbexamples.s3.us-east-2.amazonaws.com/dbexamples/ex15939en.mp3","recordId":15939,"dateCreated":"2024-01-30T19:52:36Z","dateModified":"2024-11-14T22:00:11Z","errorCoachReport":false},{"spanishExample":"No ganamos, el juego fue terrible.","englishTranslation":"We didn’t win, the game was terrible.","spanglish":"esp","vocabIncluded":["\"el\": \"the\" for masculine nouns","\"no\": \"not\", or \"n't\" in \"didn't\", \"wouldn't\", etc.","fue: \"was\", \"he/she/it was\" (Ser, preterite, 3rd person)","ganamos: won/earned, we won/earned (Ganar, preterite, 1st person plural)","juego: game (masc. noun)","terrible: terrible (adjective)"],"vocabComplete":true,"spanishAudioLa":"https://dbexamples.s3.us-east-2.amazonaws.com/dbexamples/ex15940la.mp3","englishAudio":"https://dbexamples.s3.us-east-2.amazonaws.com/dbexamples/ex15940en.mp3","recordId":15940,"dateCreated":"2024-01-30T19:52:36Z","dateModified":"2024-11-14T22:00:11Z","errorCoachReport":false},{"spanishExample":"La entrada de este sitio está en el otro lado de la plaza.","englishTranslation":"The entrance of this site is on the other side of the plaza.","spanglish":"esp","vocabIncluded":["\"de\": \"of\" as in \"type of\"","\"el\": \"the\" for masculine nouns","\"en\": \"on\"","\"la\": \"the\" for feminine nouns","entrada: entrance (fem. noun)","este: \"this...\" before a masculine noun","está: \"is\", \"he/she/it is\" (Estar, present, 3rd person)","lado: __ (. noun)","otro/otra: \"other\", \"another\" (adjective)","plaza: plaza/square (fem. noun)","sitio: site (masc. noun)"],"vocabComplete":true,"spanishAudioLa":"","englishAudio":"","recordId":15941,"dateCreated":"2024-01-30T19:52:36Z","dateModified":"2024-05-02T16:30:39Z","errorCoachReport":false},{"spanishExample":"Usó la acera porque era segura.","englishTranslation":"He used the sidewalk because it was safe.","spanglish":"esp","vocabIncluded":["\"la\": \"the\" for feminine nouns","acera: sidewalk (fem. noun)","era: \"was\", \"he/she/it was\" (Ser, imperfect, 3rd person)","porque: \"because\" (conjunction)","seguro: adjective meaning \"safe\" or \"secure\" when used with Ser","usó: used, he/she/it used (Usar, preterite, 3rd person)"],"vocabComplete":true,"spanishAudioLa":"https://dbexamples.s3.us-east-2.amazonaws.com/dbexamples/ex15942la.mp3","englishAudio":"https://dbexamples.s3.us-east-2.amazonaws.com/dbexamples/ex15942en.mp3","recordId":15942,"dateCreated":"2024-01-30T19:52:36Z","dateModified":"2024-11-14T22:00:11Z","errorCoachReport":false},{"spanishExample":"Nunca paga y por eso esas cosas no funcionan.","englishTranslation":"He never pays and that’s why those things don’t work.","spanglish":"esp","vocabIncluded":["\"no\": \"not\", or \"n't\" in \"didn't\", \"wouldn't\", etc.","\"por eso\": \"that's why\" or \"because of that\"","\"y\": \"and\" between items in a list","cosas: __ (. noun)","esas: \"those\" before a feminine noun","funcionan: function/work, they function/work (Funcionar, present, 3rd person plural)","nunca: \"never\" (adverb)","paga: pays, he/she/it pays (Pagar, present, 3rd person)"],"vocabComplete":true,"spanishAudioLa":"https://dbexamples.s3.us-east-2.amazonaws.com/dbexamples/ex15943la.mp3","englishAudio":"https://dbexamples.s3.us-east-2.amazonaws.com/dbexamples/ex15943en.mp3","recordId":15943,"dateCreated":"2024-01-30T19:52:36Z","dateModified":"2024-11-14T22:00:11Z","errorCoachReport":false},{"spanishExample":"Usaba el teléfono que conseguimos.","englishTranslation":"I was using the phone we got.","spanglish":"esp","vocabIncluded":["\"el\": \"the\" for masculine nouns","\"que\", meaning \"that\" as a relative pronoun","conseguimos: acquired/got, we acquired/got (Conseguir, preterite, 1st person plural)","teléfono: phone/telephone (masc. noun)","usaba: used, I used (Usar, imperfect, 1st person)"],"vocabComplete":true,"spanishAudioLa":"https://dbexamples.s3.us-east-2.amazonaws.com/dbexamples/ex15944la.mp3","englishAudio":"https://dbexamples.s3.us-east-2.amazonaws.com/dbexamples/ex15944en.mp3","recordId":15944,"dateCreated":"2024-01-30T19:52:36Z","dateModified":"2024-11-14T22:00:11Z","errorCoachReport":false},{"spanishExample":"¿Conseguiste el mismo que él usa?","englishTranslation":"Did you get the same one that he uses?","spanglish":"esp","vocabIncluded":["\"el\": \"the\" for masculine nouns","\"que\", meaning \"that\" as a relative pronoun","conseguiste: acquired/got, you acquired/got (Conseguir, preterite, 2nd person)","mismo: \"same\" (adjective)","usa: uses, he/she/it uses (Usar, present, 3rd person)","él: \"he\", subject pronoun"],"vocabComplete":true,"spanishAudioLa":"https://dbexamples.s3.us-east-2.amazonaws.com/dbexamples/ex15945la.mp3","englishAudio":"https://dbexamples.s3.us-east-2.amazonaws.com/dbexamples/ex15945en.mp3","recordId":15945,"dateCreated":"2024-01-30T19:52:36Z","dateModified":"2024-11-14T22:00:11Z","errorCoachReport":false},{"spanishExample":"No has pagado, pero si pagas, lo consigues.","englishTranslation":"You haven’t paid, but if you pay, you get it.","spanglish":"esp","vocabIncluded":["\"lo\": \"him\" or \"it\" as a direct object","\"no\": \"not\", or \"n't\" in \"didn't\", \"wouldn't\", etc.","\"pero\": \"but\"","\"si\": \"if\" or \"whether\"","consigues: acquire/get, you acquire/get (Conseguir, present, 2nd person)","has: \"have\", \"you have\" before a participle (Haber, present, 2nd person)","pagado: paid (Pagar participle)","pagas: pay, you pay (Pagar, present, 2nd person)"],"vocabComplete":true,"spanishAudioLa":"https://dbexamples.s3.us-east-2.amazonaws.com/dbexamples/ex15946la.mp3","englishAudio":"https://dbexamples.s3.us-east-2.amazonaws.com/dbexamples/ex15946en.mp3","recordId":15946,"dateCreated":"2024-01-30T19:52:36Z","dateModified":"2024-11-14T22:00:11Z","errorCoachReport":false},{"spanishExample":"Consíguelo antes de que yo gane.","englishTranslation":"Get it before I win.","spanglish":"esp","vocabIncluded":["\"lo\": \"him\" or \"it\" as a direct object","\"que\", meaning \"that\" as a conjunction (even in cases where \"that\" disappears in English)","antes de: \"before\" (idiom)","consigue: acquire (Conseguir imperative)","gane: win/earn, I win/earn (Ganar, subjunctive, 1st person)","yo: \"I\", subject pronoun"],"vocabComplete":false,"spanishAudioLa":"","englishAudio":"","recordId":15947,"dateCreated":"2024-01-30T19:52:36Z","dateModified":"2025-01-20T23:06:14Z","errorCoachReport":true},{"spanishExample":"No lo consiguió, aunque lo pagó.","englishTranslation":"He didn’t get it, even though he paid for it.","spanglish":"esp","vocabIncluded":["\"lo\": \"him\" or \"it\" as a direct object","\"no\": \"not\", or \"n't\" in \"didn't\", \"wouldn't\", etc.","aunque: \"although\" / \"even though\" (conjunction)","consiguió: acquired/got, he/she/it acquired/got (Conseguir, preterite, 3rd person)","pagó: paid, he/she/it paid (Pagar, preterite, 3rd person)"],"vocabComplete":true,"spanishAudioLa":"https://dbexamples.s3.us-east-2.amazonaws.com/dbexamples/ex15948la.mp3","englishAudio":"https://dbexamples.s3.us-east-2.amazonaws.com/dbexamples/ex15948en.mp3","recordId":15948,"dateCreated":"2024-01-30T19:52:36Z","dateModified":"2024-11-14T22:00:11Z","errorCoachReport":false},{"spanishExample":"Ha estado ganando por años, no creo que tenga que pagar.","englishTranslation":"He has been winning for years, I don’t think he has to pay.","spanglish":"esp","vocabIncluded":["\"no\": \"not\", or \"n't\" in \"didn't\", \"wouldn't\", etc.","\"que\", meaning \"that\" as a conjunction (even in cases where \"that\" disappears in English)","año: __ (. noun)","creo: believe, I believe (Creer, present, 1st person)","estado: \"been\" (Estar, participle)","ganando: winning/earning (Ganar gerund)","ha: \"has\", \"he/she/it has\" before a participle (Haber, present, 3rd person)","pagar: to pay (Pagar infinitive)","por: \"for\"/\"during\", as in \"for an hour\"","tenga: \"have\", \"he/she/it have\" (Tener, subjunctive, 3rd person)","using Tener with \"que\" to indicate obligation"],"vocabComplete":true,"spanishAudioLa":"","englishAudio":"","recordId":15949,"dateCreated":"2024-01-30T19:52:36Z","dateModified":"2024-05-02T16:32:10Z","errorCoachReport":false},{"spanishExample":"Aunque pague, esto no funciona.","englishTranslation":"Even if I pay, this still doesn’t work.","spanglish":"esp","vocabIncluded":["\"esto\": \"this\", neuter (without a gendered noun)","\"no\": \"not\", or \"n't\" in \"didn't\", \"wouldn't\", etc.","aunque: \"although\" / \"even though\" (conjunction)","funciona: functions/works, he/she/it functions/works (Funcionar, present, 3rd person)","pague: pay, I pay (Pagar, subjunctive, 1st person)"],"vocabComplete":true,"spanishAudioLa":"https://dbexamples.s3.us-east-2.amazonaws.com/dbexamples/ex15950la.mp3","englishAudio":"https://dbexamples.s3.us-east-2.amazonaws.com/dbexamples/ex15950en.mp3","recordId":15950,"dateCreated":"2024-01-30T19:52:36Z","dateModified":"2024-11-14T22:00:11Z","errorCoachReport":false},{"spanishExample":"No quiero que lo use, porque estará en un infierno.","englishTranslation":"I don’t want her to use it, because she’ll be in hell.","spanglish":"esp","vocabIncluded":["\"en\": \"in\"","\"lo\": \"him\" or \"it\" as a direct object","\"no\": \"not\", or \"n't\" in \"didn't\", \"wouldn't\", etc.","\"que\", meaning \"that\" as a conjunction (even in cases where \"that\" disappears in English)","\"un\": \"a\" or \"an\" with masculine nouns","estará: \"will be\", \"he/she/it will be\" (Estar, future, 3rd person)","infierno: hell/inferno (masc. noun)","porque: \"because\" (conjunction)","quiero: \"want\", \"I want\" (Querer, present, 1st person)","use: use, he/she/it use (Usar, subjunctive, 3rd person)"],"vocabComplete":true,"spanishAudioLa":"https://dbexamples.s3.us-east-2.amazonaws.com/dbexamples/ex15951la.mp3","englishAudio":"https://dbexamples.s3.us-east-2.amazonaws.com/dbexamples/ex15951en.mp3","recordId":15951,"dateCreated":"2024-01-30T19:52:36Z","dateModified":"2024-11-14T22:00:11Z","errorCoachReport":false},{"spanishExample":"Esto es estúpido, ella siempre gana.","englishTranslation":"This is stupid, she always wins.","spanglish":"esp","vocabIncluded":["\"esto\": \"this\", neuter (without a gendered noun)","ella: \"she\", subject pronoun","es: \"is\", \"he/she/it is\" (Ser, present, 3rd person)","estúpido: stupid (adjective)","gana: wins/earns, he/she/it wins/earns (Ganar, present, 3rd person)","siempre: \"always\" (adverb)"],"vocabComplete":true,"spanishAudioLa":"https://dbexamples.s3.us-east-2.amazonaws.com/dbexamples/ex15952la.mp3","englishAudio":"https://dbexamples.s3.us-east-2.amazonaws.com/dbexamples/ex15952en.mp3","recordId":15952,"dateCreated":"2024-01-30T19:52:36Z","dateModified":"2024-11-14T22:00:11Z","errorCoachReport":false},{"spanishExample":"No gané, pero conseguí dinero.","englishTranslation":"I didn’t win, but I got money.","spanglish":"esp","vocabIncluded":["\"no\": \"not\", or \"n't\" in \"didn't\", \"wouldn't\", etc.","\"pero\": \"but\"","conseguí: acquired/got, I acquired/got (Conseguir, preterite, 1st person)","dinero: money (masc. noun)","gané: won/earned, I won/earned (Ganar, preterite, 1st person)"],"vocabComplete":true,"spanishAudioLa":"https://dbexamples.s3.us-east-2.amazonaws.com/dbexamples/ex15953la.mp3","englishAudio":"https://dbexamples.s3.us-east-2.amazonaws.com/dbexamples/ex15953en.mp3","recordId":15953,"dateCreated":"2024-01-30T19:52:36Z","dateModified":"2024-11-14T22:00:11Z","errorCoachReport":false},{"spanishExample":"¡Bienvenido al tercer piso! Es el más divertido.","englishTranslation":"Welcome to the third floor! It’s the most fun.","spanglish":"esp","vocabIncluded":["\"el\": \"the\" for masculine nouns","al: \"to the\" before a masculine noun","bienvenido","divertido: fun (adjective)","es: \"is\", \"he/she/it is\" (Ser, present, 3rd person)","más: \"more\", \"most\", \"else\" (adjective)","piso: floor/story (masc. noun)","tercero: third (ordinal adjective)"],"vocabComplete":false,"spanishAudioLa":"","englishAudio":"","recordId":15954,"dateCreated":"2024-01-30T19:52:36Z","dateModified":"2024-03-14T22:42:30Z","errorCoachReport":true},{"spanishExample":"¡Paga por algo nuevo! Tienes que conseguirlo en este espacio.","englishTranslation":"Pay for something new! You have to get it in this space.","spanglish":"esp","vocabIncluded":["\"en\": \"in\"","algo: \"something\" (pronoun)","conseguirlo: to acquire/get (Conseguir infinitive) + him/it (masc.)","espacio: space (masc. noun)","este: \"this...\" before a masculine noun","nuevo: \"new\" (adjective typically used with Ser)","paga: pay (Pagar imperative)","por: \"per\" (preposition)","tienes: \"have\", \"you have\" (Tener, present, 2nd person)","using Tener with \"que\" to indicate obligation"],"vocabComplete":true,"spanishAudioLa":"","englishAudio":"","recordId":15955,"dateCreated":"2024-01-30T19:52:36Z","dateModified":"2024-05-02T16:33:05Z","errorCoachReport":false},{"spanishExample":"La salida no es la ventana, estamos en el segundo piso.","englishTranslation":"The exit isn’t the window, we are on the second floor.","spanglish":"esp","vocabIncluded":["\"el\": \"the\" for masculine nouns","\"en\": \"on\"","\"la\": \"the\" for feminine nouns","\"no\": \"not\", or \"n't\" in \"didn't\", \"wouldn't\", etc.","es: \"is\", \"he/she/it is\" (Ser, present, 3rd person)","estamos: \"are\", \"we are\" (Estar, present, 1st person plural)","piso: floor/story (masc. noun)","salida: exit (fem. noun)","segundo: second (ordinal adjective)","ventana: window (fem. noun)"],"vocabComplete":true,"spanishAudioLa":"https://dbexamples.s3.us-east-2.amazonaws.com/dbexamples/ex15956la.mp3","englishAudio":"https://dbexamples.s3.us-east-2.amazonaws.com/dbexamples/ex15956en.mp3","recordId":15956,"dateCreated":"2024-01-30T19:52:36Z","dateModified":"2024-11-14T22:00:11Z","errorCoachReport":false},{"spanishExample":"Si quieres ganar más espacio, dímelo.","englishTranslation":"If you want to win more space, tell it to me.","spanglish":"esp","vocabIncluded":["\"si\": \"if\" or \"whether\"","dímelo: tell it to me (Decir, imperative contraction) NEEDS WORK","espacio: space (masc. noun)","ganar: to win/to earn(Ganar infinitive)","más: \"more\", \"most\", \"else\" (adjective)","quieres: \"want\", \"you want\" (Querer, present, 2nd person)"],"vocabComplete":true,"spanishAudioLa":"https://dbexamples.s3.us-east-2.amazonaws.com/dbexamples/ex15957la.mp3","englishAudio":"https://dbexamples.s3.us-east-2.amazonaws.com/dbexamples/ex15957en.mp3","recordId":15957,"dateCreated":"2024-01-30T19:52:36Z","dateModified":"2024-11-14T22:00:11Z","errorCoachReport":false},{"spanishExample":"Esto no está funcionando, el suelo no es seguro.","englishTranslation":"This isn’t working, the floor isn’t safe.","spanglish":"esp","vocabIncluded":["\"el\": \"the\" for masculine nouns","\"esto\": \"this\", neuter (without a gendered noun)","\"no\": \"not\", or \"n't\" in \"didn't\", \"wouldn't\", etc.","es: \"is\", \"he/she/it is\" (Ser, present, 3rd person)","está: \"is\", \"he/she/it is\" (Estar, present, 3rd person)","funcionando: functioning/working (Funcionar gerund)","seguro: adjective meaning \"safe\" or \"secure\" when used with Ser","suelo: ground/floor (masc. noun)"],"vocabComplete":true,"spanishAudioLa":"https://dbexamples.s3.us-east-2.amazonaws.com/dbexamples/ex15958la.mp3","englishAudio":"https://dbexamples.s3.us-east-2.amazonaws.com/dbexamples/ex15958en.mp3","recordId":15958,"dateCreated":"2024-01-30T19:52:36Z","dateModified":"2024-11-14T22:00:11Z","errorCoachReport":false},{"spanishExample":"Cuando ganan, siempre es interesante.","englishTranslation":"When they win, it’s always interesting.","spanglish":"esp","vocabIncluded":["\"cuando\": \"when\" (sometimes followed by a subjunctive)","es: \"is\", \"he/she/it is\" (Ser, present, 3rd person)","ganan: win/earn, they win/earn (Ganar, present, 3rd person plural)","interesante: interesting (adjective)","siempre: \"always\" (adverb)"],"vocabComplete":true,"spanishAudioLa":"https://dbexamples.s3.us-east-2.amazonaws.com/dbexamples/ex15959la.mp3","englishAudio":"https://dbexamples.s3.us-east-2.amazonaws.com/dbexamples/ex15959en.mp3","recordId":15959,"dateCreated":"2024-01-30T19:52:36Z","dateModified":"2024-11-14T22:00:11Z","errorCoachReport":false},{"spanishExample":"Quiero que consiga lo que ha ganado.","englishTranslation":"I want him to get what he has earned.","spanglish":"esp","vocabIncluded":["\"lo que\": \"what\" as a connector between phrases","\"que\", meaning \"that\" as a conjunction (even in cases where \"that\" disappears in English)","consiga: acquire/get, he/she/it acquire/get (Conseguir, subjunctive, 3rd person)","ganado: won/earned (Ganar participle)","ha: \"has\", \"he/she/it has\" before a participle (Haber, present, 3rd person)","quiero: \"want\", \"I want\" (Querer, present, 1st person)"],"vocabComplete":true,"spanishAudioLa":"https://dbexamples.s3.us-east-2.amazonaws.com/dbexamples/ex15960la.mp3","englishAudio":"https://dbexamples.s3.us-east-2.amazonaws.com/dbexamples/ex15960en.mp3","recordId":15960,"dateCreated":"2024-01-30T19:52:36Z","dateModified":"2024-11-14T22:00:11Z","errorCoachReport":false},{"spanishExample":"No lo usamos, así que no lo pagaré.","englishTranslation":"We didn’t use it, so I won’t pay for it.","spanglish":"esp","vocabIncluded":["\"lo\": \"him\" or \"it\" as a direct object","\"no\": \"not\", or \"n't\" in \"didn't\", \"wouldn't\", etc.","así que: \"so\", \"so that\", \"such that\" (idiom)","pagaré: will pay, I will pay (Pagar, future, 1st person)","usamos: used, we used (Usar, preterite, 1st person plural)"],"vocabComplete":true,"spanishAudioLa":"https://dbexamples.s3.us-east-2.amazonaws.com/dbexamples/ex15961la.mp3","englishAudio":"https://dbexamples.s3.us-east-2.amazonaws.com/dbexamples/ex15961en.mp3","recordId":15961,"dateCreated":"2024-01-30T19:52:36Z","dateModified":"2024-11-14T22:00:11Z","errorCoachReport":false},{"spanishExample":"Quiere que use la próxima salida.","englishTranslation":"He wants me to use the next exit.","spanglish":"esp","vocabIncluded":["\"la\": \"the\" for feminine nouns","\"que\", meaning \"that\" as a conjunction (even in cases where \"that\" disappears in English)","próxima: next (adjective)","quiere: \"wants\", \"he/she/it wants\" (Querer, present, 3rd person)","salida: exit (fem. noun)","use: use, I use (Usar, subjunctive, 1st person)"],"vocabComplete":true,"spanishAudioLa":"https://dbexamples.s3.us-east-2.amazonaws.com/dbexamples/ex15962la.mp3","englishAudio":"https://dbexamples.s3.us-east-2.amazonaws.com/dbexamples/ex15962en.mp3","recordId":15962,"dateCreated":"2024-01-30T19:52:36Z","dateModified":"2024-11-14T22:00:11Z","errorCoachReport":false},{"spanishExample":"¿Sabes la dirección para nuestro destino?","englishTranslation":"Do you know the address for our destination?","spanglish":"esp","vocabIncluded":["\"la\": \"the\" for feminine nouns","\"nuestro\": \"our\" or \"ours\"","destino: destination (masc. noun)","dirección: direction/address (fem. noun)","sabes: \"know\", \"you know\" (Saber, present, 2nd person)"],"vocabComplete":false,"spanishAudioLa":"","englishAudio":"","recordId":15963,"dateCreated":"2024-01-30T19:52:36Z","dateModified":"2024-03-14T22:27:12Z","errorCoachReport":true},{"spanishExample":"Vivo en un nuevo estado donde usan esto todo el tiempo.","englishTranslation":"I live in a new state where they use this all the time.","spanglish":"esp","vocabIncluded":["\"el\": \"the\" for masculine nouns","\"en\": \"in\"","\"esto\": \"this\", neuter (without a gendered noun)","\"un\": \"a\" or \"an\" with masculine nouns","donde: \"where\" as a conjunction","estado: state (place) (masc. noun)","nuevo: \"new\" (adjective typically used with Ser)","tiempo: __ (. noun)","todo: all/every (indefinite adjective)","usan: use, they use (Usar, present, 3rd person plural)","vivo: live, I live (Vivir, present, 1st person)"],"vocabComplete":true,"spanishAudioLa":"https://dbexamples.s3.us-east-2.amazonaws.com/dbexamples/ex15964la.mp3","englishAudio":"https://dbexamples.s3.us-east-2.amazonaws.com/dbexamples/ex15964en.mp3","recordId":15964,"dateCreated":"2024-01-30T19:52:36Z","dateModified":"2024-11-14T22:00:11Z","errorCoachReport":false},{"spanishExample":"Lo conseguiré cuando llegue a mi destino.","englishTranslation":"I’ll get it when I get to my destination.","spanglish":"esp","vocabIncluded":["\"a\": \"to\", indicating direction/movement","\"cuando\": \"when\" (sometimes followed by a subjunctive)","\"lo\": \"him\" or \"it\" as a direct object","\"mi\": \"my\" with singular nouns","conseguiré: will acquire/get, I will acquire/get (Conseguir, future, 1st person)","destino: destination (masc. noun)","llegue: arrive, I arrive (Llegar, subjunctive, 1st person)"],"vocabComplete":true,"spanishAudioLa":"https://dbexamples.s3.us-east-2.amazonaws.com/dbexamples/ex15965la.mp3","englishAudio":"https://dbexamples.s3.us-east-2.amazonaws.com/dbexamples/ex15965en.mp3","recordId":15965,"dateCreated":"2024-01-30T19:52:36Z","dateModified":"2024-11-14T22:00:11Z","errorCoachReport":false},{"spanishExample":"Pagará por las cosas que ha estado usando.","englishTranslation":"He’ll pay for the things he’s been using.","spanglish":"esp","vocabIncluded":["\"que\", meaning \"that\" as a relative pronoun","cosas: __ (. noun)","estado: \"been\" (Estar, participle)","ha: \"has\", \"he/she/it has\" before a participle (Haber, present, 3rd person)","las: \"the\" for plural feminine nouns","pagará: will pay, he/she/it will pay (Pagar, future, 3rd person)","por: \"per\" (preposition)","usando: using (Usar gerund)"],"vocabComplete":true,"spanishAudioLa":"https://dbexamples.s3.us-east-2.amazonaws.com/dbexamples/ex15966la.mp3","englishAudio":"https://dbexamples.s3.us-east-2.amazonaws.com/dbexamples/ex15966en.mp3","recordId":15966,"dateCreated":"2024-01-30T19:52:36Z","dateModified":"2024-11-14T22:00:11Z","errorCoachReport":false},{"spanishExample":"Usaba mis cosas sin decírmelo.","englishTranslation":"He was using my things without telling me it.","spanglish":"esp","vocabIncluded":["\"mis\": \"my\" with plural nouns","cosas: __ (. noun)","decírmelo: to tell it to me (Decir infinitive+ contraction) ","sin: \"without\" (preposition)","usaba: used, he/she/it used (Usar, imperfect, 3rd person)"],"vocabComplete":true,"spanishAudioLa":"https://dbexamples.s3.us-east-2.amazonaws.com/dbexamples/ex15967la.mp3","englishAudio":"https://dbexamples.s3.us-east-2.amazonaws.com/dbexamples/ex15967en.mp3","recordId":15967,"dateCreated":"2024-01-30T19:52:36Z","dateModified":"2024-11-14T22:00:11Z","errorCoachReport":false},{"spanishExample":"Si conseguimos suficientes personas, el parque funcionará.","englishTranslation":"If we get enough people, the park will work.","spanglish":"esp","vocabIncluded":["\"el\": \"the\" for masculine nouns","\"si\": \"if\" or \"whether\"","conseguimos: acquire/get, we acquire/get (Conseguir, present, 1st person plural)","funcionará: will function/work, he/she/it will function/work (Funcionar, future, 3rd person)","parque: park (masc. noun)","persona: __ (. noun)","suficiente: \"enough\" (adjective)"],"vocabComplete":true,"spanishAudioLa":"","englishAudio":"","recordId":15968,"dateCreated":"2024-01-30T19:52:36Z","dateModified":"2024-05-02T16:35:32Z","errorCoachReport":false},{"spanishExample":"Yo siempre uso la ventana de la sala, pero tú no puedes usarla.","englishTranslation":"I always use the living room window, but you can’t use it.","spanglish":"esp","vocabIncluded":["\"de\": \"of\" as in \"type of\"","\"la\": \"the\" for feminine nouns","\"no\": \"not\", or \"n't\" in \"didn't\", \"wouldn't\", etc.","\"pero\": \"but\"","puedes: \"can\", \"you can\" (Poder, present, 2nd person)","sala: room (fem. noun)","siempre: \"always\" (adverb)","tú: \"you\", subject pronoun","usarla: to use (Usar infinitive) +her/it (fem)","uso: use, I use (Usar, present, 1st person)","ventana: window (fem. noun)","yo: \"I\", subject pronoun"],"vocabComplete":true,"spanishAudioLa":"","englishAudio":"","recordId":15969,"dateCreated":"2024-01-30T19:52:36Z","dateModified":"2024-05-02T16:35:39Z","errorCoachReport":false},{"spanishExample":"No funcionó, esto aún es un infierno.","englishTranslation":"It didn’t work, this is still hell.","spanglish":"esp","vocabIncluded":["\"esto\": \"this\", neuter (without a gendered noun)","\"no\": \"not\", or \"n't\" in \"didn't\", \"wouldn't\", etc.","\"un\": \"a\" or \"an\" with masculine nouns","aún: \"still/yet\" (adverb)","es: \"is\", \"he/she/it is\" (Ser, present, 3rd person)","funcionó: functioned/worked, he/she/it functioned/worked  (Funcionar, preterite, 3rd person)","infierno: hell/inferno (masc. noun)"],"vocabComplete":true,"spanishAudioLa":"https://dbexamples.s3.us-east-2.amazonaws.com/dbexamples/ex15970la.mp3","englishAudio":"https://dbexamples.s3.us-east-2.amazonaws.com/dbexamples/ex15970en.mp3","recordId":15970,"dateCreated":"2024-01-30T19:52:36Z","dateModified":"2024-11-14T22:00:11Z","errorCoachReport":false},{"spanishExample":"Use la carretera, o si no puede, dígamelo.","englishTranslation":"(Formal) Use the road, or if you can’t, tell it to me.","spanglish":"esp","vocabIncluded":["\"la\": \"the\" for feminine nouns","\"no\": \"not\", or \"n't\" in \"didn't\", \"wouldn't\", etc.","\"o\": \"or\" when used between two clauses","\"si\": \"if\" or \"whether\"","carretera: road (fem. noun)","dígamelo: tell it to me (Decir, formal imperative contraction)","puede: \"can\", \"he/she/it can\" (Poder, present, 3rd person)","use: use (Usar formal imperative)"],"vocabComplete":true,"spanishAudioLa":"https://dbexamples.s3.us-east-2.amazonaws.com/dbexamples/ex15971la.mp3","englishAudio":"https://dbexamples.s3.us-east-2.amazonaws.com/dbexamples/ex15971en.mp3","recordId":15971,"dateCreated":"2024-01-30T19:52:36Z","dateModified":"2024-11-14T22:00:11Z","errorCoachReport":false},{"spanishExample":"Tienen que decírnoslo antes de decírtelo.","englishTranslation":"They have to tell it to us before telling it to you.","spanglish":"esp","vocabIncluded":["antes de: \"before\" (idiom)","decírnoslo: to tell it to us (Decir infinitive+ contraction)","decírtelo: to tell it to you (Decir infinitive+contraction)","tienen: \"have\", \"they have\" (Tener, present, 3rd person plural)","using Tener with \"que\" to indicate obligation"],"vocabComplete":true,"spanishAudioLa":"https://dbexamples.s3.us-east-2.amazonaws.com/dbexamples/ex15972la.mp3","englishAudio":"https://dbexamples.s3.us-east-2.amazonaws.com/dbexamples/ex15972en.mp3","recordId":15972,"dateCreated":"2024-01-30T19:52:36Z","dateModified":"2024-11-14T22:00:11Z","errorCoachReport":false},{"spanishExample":"Tengo que dárselo para que lo pueda usar.","englishTranslation":"I have to give it to him so he can use it.","spanglish":"esp","vocabIncluded":["\"lo\": \"him\" or \"it\" as a direct object","dárselo: to give it to him/her (Dar infinitive) + contraction","para que: \"in order that\", \"so that\" (idiom)","pueda: \"be able\", \"he/she/it be able\" (Poder, subjunctive, 3rd person)","tengo: \"have\", \"I have\" (Tener, present, 1st person)","usar: to use (Usar infinitive)","using Tener with \"que\" to indicate obligation"],"vocabComplete":true,"spanishAudioLa":"https://dbexamples.s3.us-east-2.amazonaws.com/dbexamples/ex15973la.mp3","englishAudio":"https://dbexamples.s3.us-east-2.amazonaws.com/dbexamples/ex15973en.mp3","recordId":15973,"dateCreated":"2024-01-30T19:52:36Z","dateModified":"2024-11-14T22:00:11Z","errorCoachReport":false},{"spanishExample":"Ella quiere que yo consiga un nuevo trabajo.","englishTranslation":"She wants me to get a new job.","spanglish":"esp","vocabIncluded":["\"que\", meaning \"that\" as a conjunction (even in cases where \"that\" disappears in English)","\"un\": \"a\" or \"an\" with masculine nouns","consiga: acquire/get, I acquire/get (Conseguir, subjunctive, 1st person)","ella: \"she\", subject pronoun","nuevo: \"new\" (adjective typically used with Ser)","quiere: \"wants\", \"he/she/it wants\" (Querer, present, 3rd person)","trabajo: __ (. noun)","yo: \"I\", subject pronoun"],"vocabComplete":true,"spanishAudioLa":"https://dbexamples.s3.us-east-2.amazonaws.com/dbexamples/ex15974la.mp3","englishAudio":"https://dbexamples.s3.us-east-2.amazonaws.com/dbexamples/ex15974en.mp3","recordId":15974,"dateCreated":"2024-01-30T19:52:36Z","dateModified":"2024-11-14T22:00:11Z","errorCoachReport":false}]