[{"spanishExample":"¡He tenido la mejor *family!*","englishTranslation":"I have had the best family(f)!","spanglish":"spanglish","vocabIncluded":["\"la\": \"the\" for feminine nouns","he: \"have\", \"I have\" before a participle (Haber, present, 1st person)","mejor: \"better\" (adjective)","tenido: \"had\" (Tener participle)"],"vocabComplete":true,"spanishAudioLa":"","englishAudio":"","recordId":3742,"dateCreated":"2023-06-22T18:23:21Z","dateModified":"2024-10-09T12:14:45Z","errorCoachReport":false},{"spanishExample":"¡Vamos! No *I want* que tengan que *take us.*","englishTranslation":"Let’s go! I don’t want them to have to take us.","spanglish":"spanglish","vocabIncluded":["\"no\": \"not\", or \"n't\" in \"didn't\", \"wouldn't\", etc.","\"que\", meaning \"that\" as a conjunction (even in cases where \"that\" disappears in English)","tengan: \"have\", \"they have\" (Tener, subjunctive, 3rd person plural)","using Tener with \"que\" to indicate obligation","vamos: \"let's go\" (Ir, imperative, 1st person plural)"],"vocabComplete":true,"spanishAudioLa":"","englishAudio":"","recordId":3743,"dateCreated":"2023-06-22T18:23:21Z","dateModified":"2024-10-09T12:14:54Z","errorCoachReport":false},{"spanishExample":"¡Vamos! Tendremos que *eat later.*","englishTranslation":"Let’s go! We’ll have to eat later.","spanglish":"spanglish","vocabIncluded":["tendremos: \"will have\", \"we will have\" (Tener, future, 1st person plural)","using Tener with \"que\" to indicate obligation","vamos: \"let's go\" (Ir, imperative, 1st person plural)"],"vocabComplete":true,"spanishAudioLa":"","englishAudio":"","recordId":3744,"dateCreated":"2023-06-22T18:23:21Z","dateModified":"2024-10-09T12:15:02Z","errorCoachReport":false},{"spanishExample":"¡Vayan al lugar ahora!","englishTranslation":"(All of you) Go to the place now!","spanglish":"esp","vocabIncluded":["ahora: \"now\", \"right now\" (adverb)","al: \"to the\" before a masculine noun","lugar: __ (. noun)","vayan: \"go\" (Ir, imperative, plural)"],"vocabComplete":true,"spanishAudioLa":"https://dbexamples.s3.us-east-2.amazonaws.com/dbexamples/ex3745la.mp3","englishAudio":"https://dbexamples.s3.us-east-2.amazonaws.com/dbexamples/ex3745en.mp3","recordId":3745,"dateCreated":"2023-06-22T18:23:21Z","dateModified":"2023-10-25T03:13:18Z","errorCoachReport":false},{"spanishExample":"¡Váyanse de mi casa!","englishTranslation":"(all of you) Leave my house!","spanglish":"esp","vocabIncluded":["\"de\": \"from\", indicating direction/movement","\"mi\": \"my\" with singular nouns","casa: __ (. noun)","váyanse: \"leave\" (Irse, imperative, plural)"],"vocabComplete":true,"spanishAudioLa":"https://dbexamples.s3.us-east-2.amazonaws.com/dbexamples/ex3746la.mp3","englishAudio":"https://dbexamples.s3.us-east-2.amazonaws.com/dbexamples/ex3746en.mp3","recordId":3746,"dateCreated":"2023-06-22T18:23:21Z","dateModified":"2023-10-25T03:13:18Z","errorCoachReport":false},{"spanishExample":"¡Váyase ahora!","englishTranslation":"(Formal) Leave now!","spanglish":"esp","vocabIncluded":["ahora: \"now\", \"right now\" (adverb)","váyase: \"leave\" (Irse, imperative, formal)"],"vocabComplete":true,"spanishAudioLa":"https://dbexamples.s3.us-east-2.amazonaws.com/dbexamples/ex3747la.mp3","englishAudio":"https://dbexamples.s3.us-east-2.amazonaws.com/dbexamples/ex3747en.mp3","recordId":3747,"dateCreated":"2023-06-22T18:23:21Z","dateModified":"2023-10-25T03:13:18Z","errorCoachReport":false},{"spanishExample":"¡Ve a esa casa este año!","englishTranslation":"Go to that house this year!","spanglish":"esp","vocabIncluded":["\"a\": \"to\", indicating direction/movement","año: __ (. noun)","casa: __ (. noun)","esa: \"that...\" before a feminine noun","este: \"this...\" before a masculine noun","ve: \"go\" (Ir, imperative)"],"vocabComplete":true,"spanishAudioLa":"https://dbexamples.s3.us-east-2.amazonaws.com/dbexamples/ex3748la.mp3","englishAudio":"https://dbexamples.s3.us-east-2.amazonaws.com/dbexamples/ex3748en.mp3","recordId":3748,"dateCreated":"2023-06-22T18:23:21Z","dateModified":"2023-10-25T03:13:18Z","errorCoachReport":false},{"spanishExample":"¡Vete ahora y nunca *come back!*","englishTranslation":"Leave now and never come back!","spanglish":"spanglish","vocabIncluded":["\"y\": \"and\" between clauses","ahora: \"now\", \"right now\" (adverb)","nunca: \"never\" (adverb)","vete: \"leave\" (Irse, imperative)"],"vocabComplete":true,"spanishAudioLa":"","englishAudio":"","recordId":3749,"dateCreated":"2023-06-22T18:23:21Z","dateModified":"2024-10-09T12:15:07Z","errorCoachReport":false},{"spanishExample":"¿Todo bien? Hay que hacer *the work.*","englishTranslation":"All good? There is a need to do the work.","spanglish":"spanglish","vocabIncluded":["hacer: \"to do/make\", \"doing/making\" (Hacer, infinitive)","hay: \"there is/are\" indicating existence (Haber, present, impersonal)","todo bien: \"all good/well\" (idiom)","using Haber with \"que\" to indicate that there's a need to do something"],"vocabComplete":true,"spanishAudioLa":"","englishAudio":"","recordId":3750,"dateCreated":"2023-06-22T18:23:21Z","dateModified":"2024-10-09T12:15:13Z","errorCoachReport":false},{"spanishExample":"Ella *hopes* que yo tenga que *finish the report.*","englishTranslation":"She hopes that I have to finish the report.","spanglish":"spanglish","vocabIncluded":["\"que\", meaning \"that\" as a conjunction (even in cases where \"that\" disappears in English)","ella: \"she\", subject pronoun","tenga: \"have\", \"I have\" (Tener, subjunctive, 1st person)","using Tener with \"que\" to indicate obligation","yo: \"I\", subject pronoun"],"vocabComplete":true,"spanishAudioLa":"","englishAudio":"","recordId":3751,"dateCreated":"2023-06-22T18:23:21Z","dateModified":"2024-10-09T12:15:25Z","errorCoachReport":false},{"spanishExample":"Ella lo tiene que hacer, ya que ella lo tiene.","englishTranslation":"She has to do it, since she has it.","spanglish":"esp","vocabIncluded":["\"lo\": \"him\" or \"it\" as a direct object","ella: \"she\", subject pronoun","hacer: \"to do/make\", \"doing/making\" (Hacer, infinitive)","tiene: \"has\", \"he/she/it has\" (Tener, present, 3rd person)","using Tener with \"que\" to indicate obligation","ya que: idiom meaning \"since\" in a logical sense"],"vocabComplete":true,"spanishAudioLa":"https://dbexamples.s3.us-east-2.amazonaws.com/dbexamples/ex3752la.mp3","englishAudio":"https://dbexamples.s3.us-east-2.amazonaws.com/dbexamples/ex3752en.mp3","recordId":3752,"dateCreated":"2023-06-22T18:23:21Z","dateModified":"2023-10-25T03:13:18Z","errorCoachReport":false},{"spanishExample":"Había que *clean* la casa.","englishTranslation":"There was a need to clean the house.","spanglish":"spanglish","vocabIncluded":["\"la\": \"the\" for feminine nouns","casa: __ (. noun)","había: \"there was/were\" indicating existence (Haber, imperfect, impersonal)","using Haber with \"que\" to indicate that there's a need to do something"],"vocabComplete":true,"spanishAudioLa":"","englishAudio":"","recordId":3753,"dateCreated":"2023-06-22T18:23:21Z","dateModified":"2024-10-09T12:15:34Z","errorCoachReport":false},{"spanishExample":"Habrá que *follow the rules.*","englishTranslation":"There will be a need to follow the rules.","spanglish":"spanglish","vocabIncluded":["habrá: \"there will be\" indicating existence (Haber, future, impersonal)","using Haber with \"que\" to indicate that there's a need to do something"],"vocabComplete":true,"spanishAudioLa":"","englishAudio":"","recordId":3754,"dateCreated":"2023-06-22T18:23:21Z","dateModified":"2024-10-09T12:15:40Z","errorCoachReport":false},{"spanishExample":"*I hope* que mi amiga tenga *a good week.*","englishTranslation":"I hope my friend(f) has a good week.","spanglish":"spanglish","vocabIncluded":["\"mi\": \"my\" with singular nouns","\"que\", meaning \"that\" as a conjunction (even in cases where \"that\" disappears in English)","amiga: __ (. noun)","tenga: \"have\", \"he/she/it have\" (Tener, subjunctive, 3rd person)"],"vocabComplete":true,"spanishAudioLa":"","englishAudio":"","recordId":3755,"dateCreated":"2023-06-22T18:23:21Z","dateModified":"2024-10-09T12:15:49Z","errorCoachReport":false},{"spanishExample":"*I think* que lo tenía en su casa.","englishTranslation":"I think he had it at his house.","spanglish":"spanglish","vocabIncluded":["\"en\": \"at\" indicating location","\"lo\": \"him\" or \"it\" as a direct object","\"que\", meaning \"that\" as a conjunction (even in cases where \"that\" disappears in English)","\"su\": \"his\"/\"her\"/\"their\" with singular nouns","casa: __ (. noun)","tenía: \"had\", \"he/she/it had\" (Tener, imperfect, 3rd person)"],"vocabComplete":true,"spanishAudioLa":"","englishAudio":"","recordId":3756,"dateCreated":"2023-06-22T18:23:21Z","dateModified":"2024-10-09T12:15:56Z","errorCoachReport":false},{"spanishExample":"*I want* que lo tengamos que hacer.","englishTranslation":"I want us to have to do it.","spanglish":"spanglish","vocabIncluded":["\"lo\": \"him\" or \"it\" as a direct object","\"que\", meaning \"that\" as a conjunction (even in cases where \"that\" disappears in English)","hacer: \"to do/make\", \"doing/making\" (Hacer, infinitive)","tengamos: \"have\", \"we have\" (Tener, subjunctive, 1st person plural)","using Tener with \"que\" to indicate obligation"],"vocabComplete":true,"spanishAudioLa":"","englishAudio":"","recordId":3757,"dateCreated":"2023-06-22T18:23:21Z","dateModified":"2024-10-09T12:16:02Z","errorCoachReport":false},{"spanishExample":"La chica tuvo un *accident last week.*","englishTranslation":"The girl had an accident last week.","spanglish":"spanglish","vocabIncluded":["\"la\": \"the\" for feminine nouns","\"un\": \"a\" or \"an\" with masculine nouns","chica: __ (. noun)","tuvo: \"had\", \"he/she/it had\" (Tener, preterite, 3rd person)"],"vocabComplete":true,"spanishAudioLa":"","englishAudio":"","recordId":3758,"dateCreated":"2023-06-22T18:23:21Z","dateModified":"2024-10-09T12:16:07Z","errorCoachReport":false},{"spanishExample":"La tuve por un día.","englishTranslation":"I had it(f) for one day.","spanglish":"esp","vocabIncluded":["\"la\": \"her\" or \"it\" as a direct object","\"un\": \"a\" or \"an\" with masculine nouns","día: __ (. noun)","por: \"for\"/\"during\", as in \"for an hour\"","tuve: \"had\", \"I had\" (Tener, preterite, 1st person)"],"vocabComplete":true,"spanishAudioLa":"https://dbexamples.s3.us-east-2.amazonaws.com/dbexamples/ex3759la.mp3","englishAudio":"https://dbexamples.s3.us-east-2.amazonaws.com/dbexamples/ex3759en.mp3","recordId":3759,"dateCreated":"2023-06-22T18:23:21Z","dateModified":"2023-10-25T03:13:18Z","errorCoachReport":false},{"spanishExample":"Lo tendrán que hacer por su amigo.","englishTranslation":"They will have to do it on behalf of their friend.","spanglish":"esp","vocabIncluded":["\"lo\": \"him\" or \"it\" as a direct object","\"su\": \"his\"/\"her\"/\"their\" with singular nouns","amigo: __ (. noun)","hacer: \"to do/make\", \"doing/making\" (Hacer, infinitive)","por: \"on behalf of\" (preposition)","tendrán: \"will have\", \"they will have\" (Tener, future, 3rd person plural)","using Tener with \"que\" to indicate obligation"],"vocabComplete":true,"spanishAudioLa":"https://dbexamples.s3.us-east-2.amazonaws.com/dbexamples/ex3760la.mp3","englishAudio":"https://dbexamples.s3.us-east-2.amazonaws.com/dbexamples/ex3760en.mp3","recordId":3760,"dateCreated":"2023-06-22T18:23:21Z","dateModified":"2023-10-24T22:29:59Z","errorCoachReport":false},{"spanishExample":"Los dos tienen un amigo aquí.","englishTranslation":"Both of them(m) have a friend(m) here.","spanglish":"esp","vocabIncluded":["\"los dos\" or \"las dos\": \"both\"","\"un\": \"a\" or \"an\" with masculine nouns","amigo: __ (. noun)","aquí: \"here\", adverb","tienen: \"have\", \"they have\" (Tener, present, 3rd person plural)"],"vocabComplete":true,"spanishAudioLa":"https://dbexamples.s3.us-east-2.amazonaws.com/dbexamples/ex3761la.mp3","englishAudio":"https://dbexamples.s3.us-east-2.amazonaws.com/dbexamples/ex3761en.mp3","recordId":3761,"dateCreated":"2023-06-22T18:23:21Z","dateModified":"2023-10-24T22:29:59Z","errorCoachReport":false},{"spanishExample":"Me tendrás que *tell* lo que *you know.*","englishTranslation":"You will have to tell me what you know.","spanglish":"spanglish","vocabIncluded":["\"lo que\": \"what\" as a connector between phrases","me: \"me\" as an indirect object (\"to me\", \"for me\")","tendrás: \"will have\", \"you will have\" (Tener, future, 2nd person)","using Tener with \"que\" to indicate obligation"],"vocabComplete":true,"spanishAudioLa":"","englishAudio":"","recordId":3762,"dateCreated":"2023-06-22T18:23:21Z","dateModified":"2024-10-09T12:16:17Z","errorCoachReport":false},{"spanishExample":"No tengo que hacer lo que *you want.*","englishTranslation":"I don’t have to do what you want.","spanglish":"spanglish","vocabIncluded":["\"lo que\": \"what\" as a connector between phrases","\"no\": \"not\", or \"n't\" in \"didn't\", \"wouldn't\", etc.","hacer: \"to do/make\", \"doing/making\" (Hacer, infinitive)","tengo: \"have\", \"I have\" (Tener, present, 1st person)","using Tener with \"que\" to indicate obligation"],"vocabComplete":true,"spanishAudioLa":"","englishAudio":"","recordId":3763,"dateCreated":"2023-06-22T18:23:21Z","dateModified":"2024-10-09T12:16:22Z","errorCoachReport":false},{"spanishExample":"No tenías que estar ahí.","englishTranslation":"You didn’t have to be there.","spanglish":"esp","vocabIncluded":["\"no\": \"not\", or \"n't\" in \"didn't\", \"wouldn't\", etc.","ahí: adverb meaning \"there\", especially when close to the speaker or listener","estar: \"to be\" / \"being\", infinitive","tenías: \"had\", \"you had\" (Tener, imperfect, 2nd person)","using Tener with \"que\" to indicate obligation"],"vocabComplete":true,"spanishAudioLa":"https://dbexamples.s3.us-east-2.amazonaws.com/dbexamples/ex3764la.mp3","englishAudio":"https://dbexamples.s3.us-east-2.amazonaws.com/dbexamples/ex3764en.mp3","recordId":3764,"dateCreated":"2023-06-22T18:23:21Z","dateModified":"2023-10-25T03:13:18Z","errorCoachReport":false},{"spanishExample":"Por favor, ten uno en tu casa.","englishTranslation":"Please, have one in your house.","spanglish":"esp","vocabIncluded":["\"en\": \"in\"","\"tu\": \"your\" with singular nouns","casa: __ (. noun)","por favor: \"please\" (idiom)","ten: \"have\" (Tener, imperative, 2nd person)","uno/una to mean \"one\" (number)"],"vocabComplete":true,"spanishAudioLa":"https://dbexamples.s3.us-east-2.amazonaws.com/dbexamples/ex3765la.mp3","englishAudio":"https://dbexamples.s3.us-east-2.amazonaws.com/dbexamples/ex3765en.mp3","recordId":3765,"dateCreated":"2023-06-22T18:23:21Z","dateModified":"2023-10-25T03:13:18Z","errorCoachReport":false},{"spanishExample":"Te *I’ll visit* cuando tengas *new games.*","englishTranslation":"I’ll visit you when you have new games.","spanglish":"spanglish","vocabIncluded":["\"cuando\": \"when\" (sometimes followed by a subjunctive)","\"te\": \"you\" as a direct object","tengas: \"have\", \"you have\" (Tener, subjunctive, 2nd person)"],"vocabComplete":true,"spanishAudioLa":"","englishAudio":"","recordId":3766,"dateCreated":"2023-06-22T18:23:21Z","dateModified":"2024-10-09T12:16:33Z","errorCoachReport":false},{"spanishExample":"Tendrá dos casas otra vez.","englishTranslation":"He will have two houses again.","spanglish":"esp","vocabIncluded":["casas: __ (. noun)","dos: \"two\" (number)","otra vez: \"again\" (idiom)","tendrá: \"will have\", \"he/she/it will have\" (Tener, future, 3rd person)"],"vocabComplete":true,"spanishAudioLa":"https://dbexamples.s3.us-east-2.amazonaws.com/dbexamples/ex3767la.mp3","englishAudio":"https://dbexamples.s3.us-east-2.amazonaws.com/dbexamples/ex3767en.mp3","recordId":3767,"dateCreated":"2023-06-22T18:23:21Z","dateModified":"2023-10-25T03:13:18Z","errorCoachReport":false},{"spanishExample":"Tendré que *move* al *finishing school.*","englishTranslation":"I’ll have to move upon finishing school.","spanglish":"spanglish","vocabIncluded":["al: \"upon\" or \"when\" before an infinitive","tendré: \"will have\", \"I will have\" (Tener, future, 1st person)","using Tener with \"que\" to indicate obligation"],"vocabComplete":true,"spanishAudioLa":"","englishAudio":"","recordId":3768,"dateCreated":"2023-06-22T18:23:21Z","dateModified":"2024-10-09T12:16:51Z","errorCoachReport":false},{"spanishExample":"Tenía que *share* las otras cosas con mi amiga.","englishTranslation":"I had to share the other things with my friend(f).","spanglish":"spanglish","vocabIncluded":["\"mi\": \"my\" with singular nouns","amiga: __ (. noun)","con: \"with\"","cosas: __ (. noun)","las: \"the\" for plural feminine nouns","otro/otra: \"other\", \"another\" (adjective)","tenía: \"had\", \"I had\" (Tener, imperfect, 1st person)","using Tener with \"que\" to indicate obligation"],"vocabComplete":true,"spanishAudioLa":"","englishAudio":"","recordId":3769,"dateCreated":"2023-06-22T18:23:21Z","dateModified":"2024-10-09T12:16:58Z","errorCoachReport":false},{"spanishExample":"Teníamos tres *books.*","englishTranslation":"We had three books.","spanglish":"spanglish","vocabIncluded":["teníamos: \"had\", \"we had\" (Tener, imperfect, 1st person plural)","tres: \"three\" (number)"],"vocabComplete":true,"spanishAudioLa":"","englishAudio":"","recordId":3770,"dateCreated":"2023-06-22T18:23:21Z","dateModified":"2024-10-09T12:17:03Z","errorCoachReport":false},{"spanishExample":"Tenían que tener solo una casa.","englishTranslation":"They had to have only one house.","spanglish":"esp","vocabIncluded":["\"una\": \"a\" or \"an\" with feminine nouns","casa: __ (. noun)","solo: \"only\"/\"just\" (adverb)","tener: \"to have\" (infinitive)","tenían: \"had\", \"they had\" (Tener, imperfect, 3rd person plural)","using Tener with \"que\" to indicate obligation"],"vocabComplete":true,"spanishAudioLa":"https://dbexamples.s3.us-east-2.amazonaws.com/dbexamples/ex3771la.mp3","englishAudio":"https://dbexamples.s3.us-east-2.amazonaws.com/dbexamples/ex3771en.mp3","recordId":3771,"dateCreated":"2023-06-22T18:23:21Z","dateModified":"2023-10-24T22:29:59Z","errorCoachReport":false},{"spanishExample":"Tienes que *clean your room* ahora; tienes muchas cosas.","englishTranslation":"You have to clean your room now; you have a lot of things.","spanglish":"spanglish","vocabIncluded":["ahora: \"now\", \"right now\" (adverb)","cosas: __ (. noun)","mucha/muchas: \"much\"/\"many\" as a pronoun","tienes: \"have\", \"you have\" (Tener, present, 2nd person)","using Tener with \"que\" to indicate obligation"],"vocabComplete":true,"spanishAudioLa":"","englishAudio":"","recordId":3772,"dateCreated":"2023-06-22T18:23:21Z","dateModified":"2024-10-09T12:17:10Z","errorCoachReport":false},{"spanishExample":"Vámonos para tener eso.","englishTranslation":"Let’s leave in order to have that.","spanglish":"esp","vocabIncluded":["\"eso\": \"that\", neuter (without a gendered noun)","para: \"in order\", \"in order to\" before an infinitive","tener: \"to have\" (infinitive)","vámonos: \"let's leave\" (Irse, imperative, 1st person plural)"],"vocabComplete":true,"spanishAudioLa":"https://dbexamples.s3.us-east-2.amazonaws.com/dbexamples/ex3773la.mp3","englishAudio":"https://dbexamples.s3.us-east-2.amazonaws.com/dbexamples/ex3773en.mp3","recordId":3773,"dateCreated":"2023-06-22T18:23:21Z","dateModified":"2023-10-25T03:13:18Z","errorCoachReport":false},{"spanishExample":"Ya está, ya no los tenemos.","englishTranslation":"It’s done, we don’t have them anymore.","spanglish":"esp","vocabIncluded":["\"no\": \"not\", or \"n't\" in \"didn't\", \"wouldn't\", etc.","los: \"them\" as a direct object","tenemos: \"have\", \"we have\" (Tener, present, 1st person plural)","ya está: idiom meaning \"it's done\", \"all done\", etc.","ya: adverb meaning \"anymore\", \"already\", and a variety of other time-related things"],"vocabComplete":true,"spanishAudioLa":"https://dbexamples.s3.us-east-2.amazonaws.com/dbexamples/ex3774la.mp3","englishAudio":"https://dbexamples.s3.us-east-2.amazonaws.com/dbexamples/ex3774en.mp3","recordId":3774,"dateCreated":"2023-06-22T18:23:21Z","dateModified":"2023-10-25T03:13:18Z","errorCoachReport":false}]