[{"spanishExample":"¡Hágalo! Ni él ni ella lo harán.","englishTranslation":"(formal) Do it! Neither he nor she will do it.","spanglish":"esp","vocabIncluded":["\"lo\": \"him\" or \"it\" as a direct object","ella: \"she\", subject pronoun","harán: __, they will __ (Hacer, future, 3rd person plural)","hágalo: \"do/make it\" (Hacer, imperative, formal)","ni: \"neither\"/\"nor\" (conjunction)","él: \"he\", subject pronoun"],"vocabComplete":true,"spanishAudioLa":"","englishAudio":"","recordId":13787,"dateCreated":"2023-12-19T22:48:32Z","dateModified":"2024-04-12T16:52:40Z","errorCoachReport":false},{"spanishExample":"¡Hazlo! *Earlier* hacías todo lo que te *we told.*","englishTranslation":"Do it! Earlier you used to do everything that we told you.","spanglish":"spanglish","vocabIncluded":["\"lo que\": \"what\" as a connector between phrases","hacías: \"were doing/making\", \"you were doing/making\" (Hacer, imperfect, 2nd person)","hazlo: \"do/make it\" (Hacer, imperative)","te: \"you\" as an indirect object (\"to you\", \"for you\")","todo lo que: \"all that\", \"everything that\" (idiom)"],"vocabComplete":true,"spanishAudioLa":"","englishAudio":"","recordId":13788,"dateCreated":"2023-12-19T22:48:32Z","dateModified":"2024-10-09T10:59:48Z","errorCoachReport":false},{"spanishExample":"¡Haz lo que te *they tell!* Ellos no lo hacen.","englishTranslation":"Do what they tell you! They don’t do it.","spanglish":"spanglish","vocabIncluded":["\"lo que\": \"what\" as a connector between phrases","\"lo\": \"him\" or \"it\" as a direct object","\"no\": \"not\", or \"n't\" in \"didn't\", \"wouldn't\", etc.","ellos: \"they\", subject pronoun","hacen: \"do/make\", \"they do/make\" (Hacer, present, 3rd person plural)","haz: \"do/make\" (Hacer, imperative)","te: \"you\" as an indirect object (\"to you\", \"for you\")"],"vocabComplete":true,"spanishAudioLa":"","englishAudio":"","recordId":13789,"dateCreated":"2023-12-19T22:48:32Z","dateModified":"2024-10-09T11:00:00Z","errorCoachReport":false},{"spanishExample":"Ella hacía eso *before*, pero ahora no lo haría.","englishTranslation":"She used to do that before, but now she would not do it.","spanglish":"spanglish","vocabIncluded":["\"eso\": \"that\", neuter (without a gendered noun)","\"lo\": \"him\" or \"it\" as a direct object","\"no\": \"not\", or \"n't\" in \"didn't\", \"wouldn't\", etc.","\"pero\": \"but\"","ahora: \"now\", \"right now\" (adverb)","ella: \"she\", subject pronoun","hacía: \"was doing/making\", \"he/she/it was doing/making\" (Hacer, imperfect, 3rd person)","haría: \"would do/make\", \"he/she/it would do/make\" (Hacer, conditional, 3rd person)"],"vocabComplete":true,"spanishAudioLa":"","englishAudio":"","recordId":13790,"dateCreated":"2023-12-19T22:48:32Z","dateModified":"2024-10-09T11:00:09Z","errorCoachReport":false},{"spanishExample":"¿Así que no fuiste? Hasta ellos fueron.","englishTranslation":"So you didn’t go? Even they went.","spanglish":"esp","vocabIncluded":["\"no\": \"not\", or \"n't\" in \"didn't\", \"wouldn't\", etc.","así que: \"so\", \"so that\", \"such that\" (idiom)","ellos: \"they\", subject pronoun","fueron: \"went\", \"they went\" (Ir, preterite, 3rd person plural)","fuiste: \"went\", \"you went\" (Ir, preterite, 2nd person)","hasta: \"even\" (adverb)"],"vocabComplete":true,"spanishAudioLa":"","englishAudio":"","recordId":13791,"dateCreated":"2023-12-19T22:48:32Z","dateModified":"2024-04-12T16:56:34Z","errorCoachReport":false},{"spanishExample":"Eso tiene que hacerse hasta ese año.","englishTranslation":"That has to be done until that year.","spanglish":"esp","vocabIncluded":["\"eso\": \"that\", neuter (without a gendered noun)","año: __ (. noun)","ese: \"that...\" before a masculine noun","hacerse: __ (Hacer infinitive) + CONTRACTION","hasta: \"until\", \"to\", \"up to\" (preposition)","tiene: \"has\", \"he/she/it has\" (Tener, present, 3rd person)","using Tener with \"que\" to indicate obligation"],"vocabComplete":true,"spanishAudioLa":"","englishAudio":"","recordId":13792,"dateCreated":"2023-12-19T22:48:32Z","dateModified":"2024-04-12T16:57:35Z","errorCoachReport":false},{"spanishExample":"Ellos lo tienen todo sí o sí.","englishTranslation":"They have it all either way.","spanglish":"esp","vocabIncluded":["\"lo\": \"him\" or \"it\" as a direct object","ellos: \"they\", subject pronoun","lo + Tener + todo: \"to have it all\" (idiom)","sí o sí: \"either way\" (idiom)","tienen: \"have\", \"they have\" (Tener, present, 3rd person plural)"],"vocabComplete":true,"spanishAudioLa":"","englishAudio":"","recordId":13793,"dateCreated":"2023-12-19T22:48:32Z","dateModified":"2024-04-12T16:59:23Z","errorCoachReport":false},{"spanishExample":"Ellos nunca *wanted* hacerte ese favor.","englishTranslation":"They never wanted to do you that favor.","spanglish":"spanglish","vocabIncluded":["ellos: \"they\", subject pronoun","ese: \"that...\" before a masculine noun","favor: __ (. noun)","hacerte (contraction)","nunca: \"never\" (adverb)"],"vocabComplete":true,"spanishAudioLa":"","englishAudio":"","recordId":13794,"dateCreated":"2023-12-19T22:48:32Z","dateModified":"2024-10-09T11:00:17Z","errorCoachReport":false},{"spanishExample":"¿Cómo que lo haremos nosotros?","englishTranslation":"What do you mean we will do it?","spanglish":"esp","vocabIncluded":["\"lo\": \"him\" or \"it\" as a direct object","cómo que: \"what do you mean...?\" (idiom)","haremos: \"will do/make\", \"we will do/make\" (Hacer, future, 1st person plural)","nosotros: \"we\", subject pronoun"],"vocabComplete":true,"spanishAudioLa":"","englishAudio":"","recordId":13795,"dateCreated":"2023-12-19T22:48:32Z","dateModified":"2024-04-12T17:01:12Z","errorCoachReport":false},{"spanishExample":"¿Quién va a ir? Tú lo hiciste otra vez.","englishTranslation":"Who is going to go? You did it another time.","spanglish":"esp","vocabIncluded":["\"lo\": \"him\" or \"it\" as a direct object","hiciste: \"did/made\", \"you did/made\" (Hacer, preterite, 2nd person)","ir: \"to go\", \"going\" (Ir, infinitive)","otra vez: \"again\" (idiom)","quién: \"who\" (interrogative pronoun)","tú: \"you\", subject pronoun","using Ir and \"a\" to put verbs in the future (e.g. \"voy a ser\")","va: \"goes\", \"he/she/it goes\" (Ir, present, 3rd person)"],"vocabComplete":true,"spanishAudioLa":"","englishAudio":"","recordId":13796,"dateCreated":"2023-12-19T22:48:32Z","dateModified":"2024-04-12T17:02:11Z","errorCoachReport":false},{"spanishExample":"¿Lo hará otro día?","englishTranslation":"Will he do it another day?","spanglish":"esp","vocabIncluded":["\"lo\": \"him\" or \"it\" as a direct object","día: __ (. noun)","hará: \"will do/make\", \"he/she/it will do/make\" (Hacer, future, 3rd person)","otro/otra: \"other\", \"another\" (adjective)"],"vocabComplete":true,"spanishAudioLa":"","englishAudio":"","recordId":13797,"dateCreated":"2023-12-19T22:48:32Z","dateModified":"2024-04-12T17:03:12Z","errorCoachReport":false},{"spanishExample":"¿Tú no lo harás?","englishTranslation":"You won’t do it?","spanglish":"esp","vocabIncluded":["\"lo\": \"him\" or \"it\" as a direct object","\"no\": \"not\", or \"n't\" in \"didn't\", \"wouldn't\", etc.","harás: \"will do/make\", \"you will do/make\" (Hacer, future, 2nd person)","tú: \"you\", subject pronoun"],"vocabComplete":true,"spanishAudioLa":"","englishAudio":"","recordId":13798,"dateCreated":"2023-12-19T22:48:32Z","dateModified":"2024-04-12T17:03:49Z","errorCoachReport":false},{"spanishExample":"Hay que hacerle ese favor.","englishTranslation":"There's a need to do her that favor.","spanglish":"esp","vocabIncluded":["ese: \"that...\" before a masculine noun","favor: __ (. noun)","hacerle (contraction)","hay: \"there is/are\" indicating existence (Haber, present, impersonal)","using Haber with \"que\" to indicate that there's a need to do something"],"vocabComplete":true,"spanishAudioLa":"","englishAudio":"","recordId":4186,"dateCreated":"2023-06-30T20:46:50Z","dateModified":"2023-10-10T15:43:16Z","errorCoachReport":false},{"spanishExample":"Hice eso para tenerte.","englishTranslation":"I did that in order to have you.","spanglish":"esp","vocabIncluded":["\"eso\": \"that\", neuter (without a gendered noun)","hice: \"did/made\", \"I did/made\" (Hacer, preterite, 1st person)","para: \"in order\", \"in order to\" before an infinitive","tenerte (contraction)"],"vocabComplete":true,"spanishAudioLa":"","englishAudio":"","recordId":4188,"dateCreated":"2023-06-30T20:46:50Z","dateModified":"2023-08-02T19:55:35Z","errorCoachReport":false},{"spanishExample":"*I want* que tú hagas eso cuando ellos también lo hagan.","englishTranslation":"I want you to do that when they also do it.","spanglish":"spanglish","vocabIncluded":["\"cuando\": \"when\" (sometimes followed by a subjunctive)","\"eso\": \"that\", neuter (without a gendered noun)","\"lo\": \"him\" or \"it\" as a direct object","\"que\", meaning \"that\" as a conjunction (even in cases where \"that\" disappears in English)","ellos: \"they\", subject pronoun","hagan: \"do/make\", \"they do/make\" (Hacer, subjunctive, 3rd person plural)","hagas: \"do/make\", \"you do/make\" (Hacer, subjunctive, 2nd person)","también: \"also\", \"as well\", \"too\" (adverb)","tú: \"you\", subject pronoun"],"vocabComplete":true,"spanishAudioLa":"","englishAudio":"","recordId":4192,"dateCreated":"2023-06-30T20:46:50Z","dateModified":"2024-10-09T11:58:34Z","errorCoachReport":false},{"spanishExample":"Juan hace eso, pero yo también lo haría.","englishTranslation":"Juan does that, but I would also do it.","spanglish":"esp","vocabIncluded":["\"eso\": \"that\", neuter (without a gendered noun)","\"lo\": \"him\" or \"it\" as a direct object","\"pero\": \"but\"","hace: \"does/makes\", \"he/she/it does/makes\" (Hacer, present, 3rd person)","haría: \"would do/make\", \"I would do/make\" (Hacer, conditional, 1st person)","también: \"also\", \"as well\", \"too\" (adverb)","yo: \"I\", subject pronoun"],"vocabComplete":true,"spanishAudioLa":"","englishAudio":"","recordId":4194,"dateCreated":"2023-06-30T20:46:50Z","dateModified":"2023-10-10T15:44:02Z","errorCoachReport":false},{"spanishExample":"Lo haré, pero cuando lo haga, no estaré ahí.","englishTranslation":"I will do it, but when I do it, I won’t be there.","spanglish":"esp","vocabIncluded":["\"cuando\": \"when\" (sometimes followed by a subjunctive)","\"lo\": \"him\" or \"it\" as a direct object","\"no\": \"not\", or \"n't\" in \"didn't\", \"wouldn't\", etc.","\"pero\": \"but\"","ahí: adverb meaning \"there\", especially when close to the speaker or listener","estaré: \"will be\", \"I will be\" (Estar, future, 1st person)","haga: \"do/make\", \"I do/make\" (Hacer, subjunctive, 1st person)","haré: \"will do/make\", \"I will do/make\" (Hacer, future, 1st person)"],"vocabComplete":true,"spanishAudioLa":"","englishAudio":"","recordId":4197,"dateCreated":"2023-06-30T20:46:50Z","dateModified":"2023-10-10T15:45:09Z","errorCoachReport":false},{"spanishExample":"Mi amigo tenía que tenerlo y por eso hizo eso.","englishTranslation":"My friend had to have it and that’s why he did that.","spanglish":"esp","vocabIncluded":["\"eso\": \"that\", neuter (without a gendered noun)","\"mi\": \"my\" with singular nouns","\"por eso\": \"that's why\" or \"because of that\"","\"y\": \"and\" between clauses","amigo: __ (. noun)","hizo: \"did/made\", \"he/she/it did/made\" (Hacer, preterite, 3rd person)","tenerlo (contraction)","tenía: \"had\", \"he/she/it had\" (Tener, imperfect, 3rd person)","using Tener with \"que\" to indicate obligation"],"vocabComplete":true,"spanishAudioLa":"","englishAudio":"","recordId":4199,"dateCreated":"2023-06-30T20:46:50Z","dateModified":"2023-08-02T19:57:43Z","errorCoachReport":false},{"spanishExample":"No *you want* irte.","englishTranslation":"You don’t want to leave.","spanglish":"spanglish","vocabIncluded":["\"no\": \"not\", or \"n't\" in \"didn't\", \"wouldn't\", etc.","irse: any use of Ir with a reflexive pronoun, changing the meaning to \"leave\"","irte (contraction)"],"vocabComplete":true,"spanishAudioLa":"","englishAudio":"","recordId":4205,"dateCreated":"2023-06-30T20:46:50Z","dateModified":"2024-10-09T11:58:40Z","errorCoachReport":false},{"spanishExample":"Nuestros amigos hicieron muchas cosas en la casa.","englishTranslation":"Our friends did a lot of things in the house.","spanglish":"esp","vocabIncluded":["\"en\": \"in\"","\"la\": \"the\" for feminine nouns","\"nuestro\": \"our\" or \"ours\"","amigo: __ (. noun)","casa: __ (. noun)","cosas: __ (. noun)","hicieron: \"did/made\", \"they did/made\" (Hacer, preterite, 3rd person plural)","mucha/muchas: \"much\"/\"many\" as a pronoun"],"vocabComplete":true,"spanishAudioLa":"","englishAudio":"","recordId":4206,"dateCreated":"2023-06-30T20:46:50Z","dateModified":"2023-08-21T21:43:05Z","errorCoachReport":false},{"spanishExample":"*They want* que él haga eso y esté por ahí.","englishTranslation":"They want him to do that and to be around.","spanglish":"spanglish","vocabIncluded":["\"eso\": \"that\", neuter (without a gendered noun)","\"que\", meaning \"that\" as a conjunction (even in cases where \"that\" disappears in English)","\"y\": \"and\" between clauses","ahí: adverb meaning \"there\", especially when close to the speaker or listener","esté: \"be\", \"he/she/it be\" (Estar, subjunctive, 3rd person)","haga: \"do/make\", \"he/she/it do/make\" (Hacer, subjunctive, 3rd person)","él: \"he\", subject pronoun"],"vocabComplete":true,"spanishAudioLa":"","englishAudio":"","recordId":4207,"dateCreated":"2023-06-30T20:46:50Z","dateModified":"2024-10-09T11:58:51Z","errorCoachReport":false},{"spanishExample":"Si hacemos eso, tendremos que irnos.","englishTranslation":"If we do that, we’ll have to leave.","spanglish":"esp","vocabIncluded":["\"eso\": \"that\", neuter (without a gendered noun)","\"si\": \"if\" or \"whether\"","hacemos: \"do/make\", \"we do/make\" (Hacer, present, 1st person plural)","irnos (contraction)","irse: any use of Ir with a reflexive pronoun, changing the meaning to \"leave\"","tendremos: \"will have\", \"we will have\" (Tener, future, 1st person plural)","using Tener with \"que\" to indicate obligation"],"vocabComplete":true,"spanishAudioLa":"","englishAudio":"","recordId":4208,"dateCreated":"2023-06-30T20:46:50Z","dateModified":"2023-10-10T15:46:09Z","errorCoachReport":false},{"spanishExample":"Siempre hago eso, pero él no *wants* irse.","englishTranslation":"I always do that, but he doesn’t want to leave.","spanglish":"spanglish","vocabIncluded":["\"eso\": \"that\", neuter (without a gendered noun)","\"no\": \"not\", or \"n't\" in \"didn't\", \"wouldn't\", etc.","\"pero\": \"but\"","hago: \"do/make\", \"I do/make\" (Hacer, present, 1st person)","irse: any use of Ir with a reflexive pronoun, changing the meaning to \"leave\"","siempre: \"always\" (adverb)","él: \"he\", subject pronoun"],"vocabComplete":true,"spanishAudioLa":"","englishAudio":"","recordId":4209,"dateCreated":"2023-06-30T20:46:50Z","dateModified":"2024-10-09T11:59:00Z","errorCoachReport":false},{"spanishExample":"Siempre lo hacía.","englishTranslation":"I always used to do it.","spanglish":"esp","vocabIncluded":["\"lo\": \"him\" or \"it\" as a direct object","hacía: \"was doing/making\", \"I was doing/making\" (Hacer, imperfect, 1st person)","siempre: \"always\" (adverb)"],"vocabComplete":true,"spanishAudioLa":"","englishAudio":"","recordId":4210,"dateCreated":"2023-06-30T20:46:50Z","dateModified":"2023-10-10T15:46:20Z","errorCoachReport":false},{"spanishExample":"Ya lo hicimos, pero tenemos que hacerlo otra vez.","englishTranslation":"We already did it, but we have to do it again.","spanglish":"esp","vocabIncluded":["\"lo\": \"him\" or \"it\" as a direct object","\"pero\": \"but\"","hacerlo (contraction)","hicimos: \"did/made\", \"we did/made\" (Hacer, preterite, 1st person plural)","otra vez: \"again\" (idiom)","tenemos: \"have\", \"we have\" (Tener, present, 1st person plural)","using Tener with \"que\" to indicate obligation","ya: adverb meaning \"anymore\", \"already\", and a variety of other time-related things"],"vocabComplete":true,"spanishAudioLa":"","englishAudio":"","recordId":4214,"dateCreated":"2023-06-30T20:46:50Z","dateModified":"2023-10-10T15:47:00Z","errorCoachReport":false},{"spanishExample":"Ya que haces eso, *I want* irme.","englishTranslation":"Since you do that, I want to leave.","spanglish":"spanglish","vocabIncluded":["\"eso\": \"that\", neuter (without a gendered noun)","haces: \"do/make\", \"you do/make\" (Hacer, present, 2nd person)","irme (contraction)","irse: any use of Ir with a reflexive pronoun, changing the meaning to \"leave\"","ya que: idiom meaning \"since\" in a logical sense"],"vocabComplete":true,"spanishAudioLa":"","englishAudio":"","recordId":4215,"dateCreated":"2023-06-30T20:46:50Z","dateModified":"2024-10-09T11:59:08Z","errorCoachReport":false}]